asynkets/__init__.py
asynkets/_sentinel.py
asynkets/async_std.py
asynkets/eventful_counter.py
asynkets/fuse.py
asynkets/pulse.py
asynkets/switch.py
asynkets/timed.py
asynkets/utils.py
asynkets-0.1.4.dist-info/WHEEL
asynkets-0.1.4.dist-info/METADATA
asynkets-0.1.4.dist-info/LICENSE
asynkets-0.1.4.dist-info/RECORD
