Metadata-Version: 2.1
Name: asynkets
Version: 0.1.4
Summary: `asynkets` is a Python library which provides miscellaneous utilities that are useful when writing `asyncio` code.
Author: Pedro Batista
Author-email: pedrovhb@gmail.com
Requires-Python: >=3.8,<4.0
Classifier: Programming Language :: Python :: 3
Classifier: Programming Language :: Python :: 3.8
Classifier: Programming Language :: Python :: 3.9
Classifier: Programming Language :: Python :: 3.10
Classifier: Programming Language :: Python :: 3.11
Requires-Dist: setuptools (==65.3.0)
Requires-Dist: wheel (==0.37.1)
